pssepath/__init__.py
pssepath/__version__.py
pssepath/core.py
pssepath/helpers.py
pssepath/pssepathinfo.py
pssepath/compat/__init__.py
pssepath/compat/_compat2.py
pssepath/compat/_compat3.py
pssepath-0.3.0.dist-info/LICENSE
pssepath-0.3.0.dist-info/METADATA
pssepath-0.3.0.dist-info/WHEEL
pssepath-0.3.0.dist-info/top_level.txt
pssepath-0.3.0.dist-info/RECORD
